git_smart_squash/VERSION
git_smart_squash/__init__.py
git_smart_squash/cli.py
git_smart_squash/dependency_validator.py
git_smart_squash/diff_parser.py
git_smart_squash/hunk_applicator.py
git_smart_squash/logger.py
git_smart_squash/post_install.py
git_smart_squash/simple_config.py
git_smart_squash/ai/__init__.py
git_smart_squash/ai/providers/__init__.py
git_smart_squash/ai/providers/simple_unified.py
git_smart_squash/strategies/__init__.py
git_smart_squash/strategies/backup_manager.py
git_smart_squash/strategies/commit_applier.py
git_smart_squash/utils/__init__.py
git_smart_squash/utils/display.py
git_smart_squash/utils/git_diff.py
git_smart_squash/utils/prompt_builder.py
git_smart_squash/utils/working_dir.py
git_smart_squash-4.0.3.dist-info/licenses/LICENSE
tests/__init__.py
tests/run_all_tests.py
tests/test_ai_integration.py
tests/test_apply_failure_restoration.py
tests/test_backup_restore.py
tests/test_cli_flags_precedence.py
tests/test_dependency_validation_integration.py
tests/test_dependency_validator.py
tests/test_e2e_hunk_application.py
tests/test_functionality_comprehensive.py
tests/test_git_diff_fallbacks.py
tests/test_idempotency.py
tests/test_instructions_feature.py
tests/test_logging.py
tests/test_openai_responses_stubbed.py
tests/test_patch_corruption_fixes.py
tests/test_providers_stubbed.py
tests/test_reasoning_all_providers.py
tests/test_utils.py
tests/test_working_directory_validation.py
git_smart_squash-4.0.3.dist-info/METADATA
git_smart_squash-4.0.3.dist-info/WHEEL
git_smart_squash-4.0.3.dist-info/entry_points.txt
git_smart_squash-4.0.3.dist-info/top_level.txt
git_smart_squash-4.0.3.dist-info/RECORD
