Metadata-Version: 2.4
Name: git-smart-squash
Version: 4.0.3
Summary: Automatically reorganize messy git commit histories into clean, semantic commits
Home-page: https://github.com/edverma/git-smart-squash
Author: Evan Verma
Author-email: edverma@icloud.com
Project-URL: Bug Reports, https://github.com/edverma/git-smart-squash/issues
Project-URL: Source, https://github.com/edverma/git-smart-squash
Project-URL: Documentation, https://github.com/edverma/git-smart-squash#readme
Keywords: git,commit,squash,rebase,conventional-commits,ai
Classifier: Development Status :: 3 - Alpha
Classifier: Intended Audience :: Developers
Classifier: Topic :: Software Development :: Version Control :: Git
Classifier: License :: OSI Approved :: MIT License
Classifier: Programming Language :: Python :: 3
Classifier: Programming Language :: Python :: 3.8
Classifier: Programming Language :: Python :: 3.9
Classifier: Programming Language :: Python :: 3.10
Classifier: Programming Language :: Python :: 3.11
Classifier: Programming Language :: Python :: 3.12
Requires-Python: >=3.8
License-File: LICENSE
Requires-Dist: pyyaml>=6.0
Requires-Dist: rich>=13.0.0
Requires-Dist: openai>=1.0.0
Requires-Dist: anthropic>=0.3.0
Requires-Dist: tiktoken>=0.5.0
Requires-Dist: google-genai>=0.0.1
Provides-Extra: dev
Requires-Dist: pytest>=7.0.0; extra == "dev"
Requires-Dist: pytest-cov>=4.0.0; extra == "dev"
Requires-Dist: black>=22.0.0; extra == "dev"
Requires-Dist: flake8>=5.0.0; extra == "dev"
Requires-Dist: mypy>=1.0.0; extra == "dev"
Dynamic: author
Dynamic: author-email
Dynamic: classifier
Dynamic: description
Dynamic: description-content-type
Dynamic: home-page
Dynamic: keywords
Dynamic: license-file
Dynamic: project-url
Dynamic: provides-extra
Dynamic: requires-dist
Dynamic: requires-python
Dynamic: summary
